prompt_block/__init__.py
prompt_block/client.py
prompt_block-0.3.dist-info/METADATA
prompt_block-0.3.dist-info/WHEEL
prompt_block-0.3.dist-info/top_level.txt
prompt_block-0.3.dist-info/RECORD
