Metadata-Version: 2.1
Name: prompt-block
Version: 0.3
Summary: Client for Prompt Block. Build your prompt library with ease.
Author: Contentify
Author-email: hi@contentify.app
Requires-Dist: requests
